huefy/README.md
huefy/__init__.py
huefy/demo.theme
huefy/hue.config
huefy/text_builder.py
huefy/theme.py
huefy/theme_manager.py
huefy/themes.d/aurora.theme
huefy/themes.d/ayu_dark.theme
huefy/themes.d/material_dark.theme
huefy/themes.d/monokai.theme
huefy/themes.d/night_owl.theme
huefy/themes.d/nord_dark.theme
huefy/themes.d/nord_light.theme
huefy/themes.d/snow_storm.theme
huefy/themes.d/vampire.theme
huefy-1.3.0.dist-info/METADATA
huefy-1.3.0.dist-info/WHEEL
huefy-1.3.0.dist-info/entry_points.txt
huefy-1.3.0.dist-info/top_level.txt
huefy-1.3.0.dist-info/RECORD
