Metadata-Version: 2.1
Name: huefy
Version: 1.3.0
Summary: Terminal color utility
Home-page: https://github.com/devinci-it/hue
Author: devinci-it
Classifier: Programming Language :: Python :: 3
Classifier: License :: OSI Approved :: MIT License
Classifier: Operating System :: OS Independent
Requires-Python: >=3.6
